odoo10_addon_product_template_tags-10.0.1.0.0-py2.7-nspkg.pth
odoo/addons/product_template_tags/README.rst
odoo/addons/product_template_tags/__init__.py
odoo/addons/product_template_tags/__manifest__.py
odoo/addons/product_template_tags/models/__init__.py
odoo/addons/product_template_tags/models/product_template.py
odoo/addons/product_template_tags/models/product_template_tag.py
odoo/addons/product_template_tags/security/product_template_rule.xml
odoo/addons/product_template_tags/security/product_template_tag.xml
odoo/addons/product_template_tags/static/description/icon.png
odoo/addons/product_template_tags/views/product_template.xml
odoo/addons/product_template_tags/views/product_template_tag.xml
odoo10_addon_product_template_tags-10.0.1.0.0.dist-info/DESCRIPTION.rst
odoo10_addon_product_template_tags-10.0.1.0.0.dist-info/METADATA
odoo10_addon_product_template_tags-10.0.1.0.0.dist-info/RECORD
odoo10_addon_product_template_tags-10.0.1.0.0.dist-info/WHEEL
odoo10_addon_product_template_tags-10.0.1.0.0.dist-info/metadata.json
odoo10_addon_product_template_tags-10.0.1.0.0.dist-info/namespace_packages.txt
odoo10_addon_product_template_tags-10.0.1.0.0.dist-info/top_level.txt
